README.rst
setup.py
Repo_Scout.egg-info/PKG-INFO
Repo_Scout.egg-info/SOURCES.txt
Repo_Scout.egg-info/dependency_links.txt
Repo_Scout.egg-info/entry_points.txt
Repo_Scout.egg-info/requires.txt
Repo_Scout.egg-info/top_level.txt
src/__init__.py
src/launcher.py
src/application/__init__.py
src/application/cli.py
src/network/__init__.py
src/network/factory/__init__.py
src/network/factory/scout_factory.py
src/network/scout/__init__.py
src/network/scout/findable.py
src/network/scout/github_scout.py
src/service/__init__.py
src/service/repo_scout.py
test/__init__.py
test/network/__init__.py
test/network/factory/__init__.py
test/network/factory/test_scout_factory.py
test/network/scout/__init__.py
test/network/scout/test_github_scout.py
test/service/__init__.py
test/service/test_repo_scout.py