Metadata-Version: 1.1
Name: Repo-Scout
Version: 1.0.0
Summary: Searches for a file in a VCS
Home-page: https://github.com/Parcks/Repo-Scout
Author: JValck
Author-email: parcks@setarit.com
License: GPLv2
Keywords: Parcks API Scout Find Repository
Platform: UNKNOWN
Classifier: Development Status :: 5 - Production/Stable
Classifier: Intended Audience :: Developers
Classifier: Intended Audience :: System Administrators
Classifier: Intended Audience :: End Users/Desktop
Classifier: License :: OSI Approved :: GNU General Public License v2 (GPLv2)
Classifier: Natural Language :: English
Classifier: Programming Language :: Python :: 2.7
Classifier: Programming Language :: Python :: 3.3
Classifier: Programming Language :: Python :: 3.4
Classifier: Programming Language :: Python :: 3.5
Classifier: Programming Language :: Python :: 3.6
